{
  "test_accuracy": 100.0,
  "class_correct": [
    14,
    11,
    28,
    5,
    1,
    8,
    1,
    4,
    4,
    3
  ],
  "class_total": [
    14,
    11,
    28,
    5,
    1,
    8,
    1,
    4,
    4,
    3
  ],
  "confusion_matrix": [
    [
      14,
      0,
      0,
      0,
      0,
      0,
      0,
      0,
      0,
      0
    ],
    [
      0,
      11,
      0,
      0,
      0,
      0,
      0,
      0,
      0,
      0
    ],
    [
      0,
      0,
      28,
      0,
      0,
      0,
      0,
      0,
      0,
      0
    ],
    [
      0,
      0,
      0,
      5,
      0,
      0,
      0,
      0,
      0,
      0
    ],
    [
      0,
      0,
      0,
      0,
      1,
      0,
      0,
      0,
      0,
      0
    ],
    [
      0,
      0,
      0,
      0,
      0,
      8,
      0,
      0,
      0,
      0
    ],
    [
      0,
      0,
      0,
      0,
      0,
      0,
      1,
      0,
      0,
      0
    ],
    [
      0,
      0,
      0,
      0,
      0,
      0,
      0,
      4,
      0,
      0
    ],
    [
      0,
      0,
      0,
      0,
      0,
      0,
      0,
      0,
      4,
      0
    ],
    [
      0,
      0,
      0,
      0,
      0,
      0,
      0,
      0,
      0,
      3
    ]
  ],
  "val_accuracy": 97.46835443037975,
  "best_epoch": 32,
  "parameters": 118794,
  "num_classes": 10,
  "class_names": [
    "notehead_filled",
    "notehead_hollow",
    "stem",
    "flag",
    "dot",
    "rest",
    "clef",
    "sharp",
    "flat",
    "natural"
  ],
  "input_dim": 3,
  "max_seq_len": 512,
  "padding": "repeat_last"
}